pkgmt/__init__.py
pkgmt/_format.py
pkgmt/changelog.py
pkgmt/cli.py
pkgmt/config.py
pkgmt/dependencies.py
pkgmt/deprecation.py
pkgmt/dev.py
pkgmt/exceptions.py
pkgmt/fail_if_invalid_changelog.py
pkgmt/fail_if_modified.py
pkgmt/fail_if_not_modified.py
pkgmt/formatting.py
pkgmt/github.py
pkgmt/hook.py
pkgmt/links.py
pkgmt/new.py
pkgmt/test.py
pkgmt/utm.py
pkgmt/versioneer.py
pkgmt/assets/__init__.py
pkgmt/assets/template/.gitignore
pkgmt/assets/template/CHANGELOG.md
pkgmt/assets/template/MANIFEST.in
pkgmt/assets/template/README.md
pkgmt/assets/template/pyproject-setup.toml
pkgmt/assets/template/pyproject.toml
pkgmt/assets/template/settings.py
pkgmt/assets/template/setup.cfg
pkgmt/assets/template/setup.py
pkgmt/assets/template/tasks.py
pkgmt/assets/template/.github/pull_request_template.md
pkgmt/assets/template/.github/workflows/ci.yml
pkgmt/assets/template/src/package_name/__init__.py
pkgmt/assets/template/src/package_name/_settings.py
pkgmt/assets/template/src/package_name/cli.py
pkgmt/assets/template/src/package_name/log.py
pkgmt/assets/template/tests/conftest.py
pkgmt/assets/template/tests/test_sample.py
pkgmt/versioner/__init__.py
pkgmt/versioner/util.py
pkgmt/versioner/versioner.py
pkgmt-0.8.3.dist-info/LICENSE
pkgmt-0.8.3.dist-info/METADATA
pkgmt-0.8.3.dist-info/WHEEL
pkgmt-0.8.3.dist-info/entry_points.txt
pkgmt-0.8.3.dist-info/top_level.txt
pkgmt-0.8.3.dist-info/RECORD
